pyxxl/__init__.py
pyxxl/ctx.py
pyxxl/enum.py
pyxxl/error.py
pyxxl/executor.py
pyxxl/log.py
pyxxl/main.py
pyxxl/prometheus.py
pyxxl/schema.py
pyxxl/server.py
pyxxl/setting.py
pyxxl/types.py
pyxxl/utils.py
pyxxl/xxl_client.py
pyxxl/logger/__init__.py
pyxxl/logger/common.py
pyxxl/logger/disk.py
pyxxl/logger/redis.py
pyxxl/tests/__init__.py
pyxxl/tests/conftest.py
pyxxl/tests/test_client.py
pyxxl/tests/test_context.py
pyxxl/tests/test_executor.py
pyxxl/tests/test_handler.py
pyxxl/tests/test_logger.py
pyxxl/tests/test_register.py
pyxxl/tests/test_setting.py
pyxxl/tests/test_utils.py
pyxxl/tests/utils.py
pyxxl/tests/api/__init__.py
pyxxl/tests/api/test_metrics.py
pyxxl/tests/api/test_server.py
pyxxl-0.4.6.dist-info/licenses/LICENSE
pyxxl-0.4.6.dist-info/METADATA
pyxxl-0.4.6.dist-info/WHEEL
pyxxl-0.4.6.dist-info/top_level.txt
pyxxl-0.4.6.dist-info/RECORD
