Metadata-Version: 2.4
Name: pyxxl
Version: 0.4.6
Summary: A Python executor for XXL-jobs
Author-email: fcfangcc <swjfc22@live.com>
License: GPL-3.0-only
Project-URL: Homepage, https://github.com/fcfangcc/pyxxl
Project-URL: Documentation, https://fcfangcc.github.io/pyxxl/latest/
Keywords: XXL,scheduled
Classifier: Framework :: AsyncIO
Classifier: Topic :: Software Development
Classifier: Topic :: Software Development :: Libraries :: Python Modules
Classifier: Operating System :: POSIX :: Linux
Classifier: Programming Language :: Python
Classifier: Programming Language :: Python :: 3.9
Classifier: Programming Language :: Python :: 3.10
Classifier: Programming Language :: Python :: 3.11
Classifier: Programming Language :: Python :: 3.12
Classifier: Programming Language :: Python :: 3.13
Requires-Python: >=3.9
License-File: LICENSE
Requires-Dist: aiofiles
Requires-Dist: aiohttp
Provides-Extra: dotenv
Requires-Dist: python-dotenv; extra == "dotenv"
Provides-Extra: metrics
Requires-Dist: prometheus-client; extra == "metrics"
Provides-Extra: redis
Requires-Dist: redis; extra == "redis"
Provides-Extra: all
Requires-Dist: redis; extra == "all"
Requires-Dist: python-dotenv; extra == "all"
Requires-Dist: prometheus-client; extra == "all"
Provides-Extra: doc
Requires-Dist: mdx-include~=1.4; extra == "doc"
Requires-Dist: mkdocs~=1.4; extra == "doc"
Requires-Dist: mkdocs-material~=9.5.23; extra == "doc"
Requires-Dist: mkdocstrings[python]~=0.20; extra == "doc"
Requires-Dist: mike; extra == "doc"
Provides-Extra: dev
Requires-Dist: mypy~=1.15; extra == "dev"
Requires-Dist: pre-commit~=3.6.0; extra == "dev"
Requires-Dist: pytest==7.1; extra == "dev"
Requires-Dist: pytest-aiohttp==1.1.0; extra == "dev"
Requires-Dist: pytest-asyncio==0.18.3; extra == "dev"
Requires-Dist: pytest-cov==3.0.0; extra == "dev"
Requires-Dist: ruff<=1; extra == "dev"
Dynamic: license-file
